Metadata-Version: 2.1
Name: autora-experimentalist-model-disagreement
Version: 2.2.0
Summary: Compares weaknesses in multiple models
Author-email: "Built by Sebastian Musslick, re-factored by Chad Williams" <sebastian_musslick@brown.edu>
License: MIT License
Project-URL: homepage, http://www.empiricalresearch.ai
Project-URL: repository, https://github.com/AutoResearch/autora-experimentalist-model-disagreement
Project-URL: documentation, https://autoresearch.github.io/autora/
Requires-Python: <4,>=3.8
License-File: LICENSE
Requires-Dist: autora-core>=3.1.0
Requires-Dist: scikit-learn
Provides-Extra: dev
Requires-Dist: autora-core[dev]; extra == "dev"
